{
  "_hash": "356af81346c1481a2ce7787207ab4c183f4880f7",
  "claims": [
    {
      "text": "Wilmar International improved supply chain traceability with RSPO-certified and audited suppliers",
      "source_sentence": "In FY2023, Wilmar International improved supply chain traceability with RSPO-certified and audited suppliers.",
      "source_page": 1
    },
    {
      "text": "Wilmar International reduced Scope 1 and Scope 2 carbon emissions intensity",
      "source_sentence": "In FY2023, Wilmar International reduced Scope 1 and Scope 2 carbon emissions intensity.",
      "source_page": 1
    },
    {
      "text": "Wilmar International lowered water intensity through recycled water initiatives",
      "source_sentence": "In FY2023, Wilmar International lowered water intensity through recycled water initiatives.",
      "source_page": 1
    },
    {
      "text": "Wilmar International upheld food safety and product quality standards",
      "source_sentence": "In FY2023, Wilmar International upheld food safety and product quality standards.",
      "source_page": 1
    },
    {
      "text": "Wilmar International protected worker safety and labour rights across operations",
      "source_sentence": "In FY2023, Wilmar International protected worker safety and labour rights across operations.",
      "source_page": 1
    },
    {
      "text": "Wilmar International strengthened its anti-corruption code of conduct and board ethics oversight",
      "source_sentence": "In FY2023, Wilmar International strengthened its anti-corruption code of conduct and board ethics oversight.",
      "source_page": 1
    }
  ]
}