{
  "_hash": "74c8bceca4b68c67b2f3ed31baf527dd028fc121",
  "claims": [
    {
      "text": "In FY2023, Default ASEAN 41 reduced Scope 1 and Scope 2 carbon emissions intensity.",
      "source_sentence": "In FY2023, Default ASEAN 41 reduced Scope 1 and Scope 2 carbon emissions intensity.",
      "source_page": 1
    },
    {
      "text": "In FY2023, Default ASEAN 41 strengthened its anti-corruption code of conduct and board ethics oversight.",
      "source_sentence": "In FY2023, Default ASEAN 41 strengthened its anti-corruption code of conduct and board ethics oversight.",
      "source_page": 1
    },
    {
      "text": "In FY2023, Default ASEAN 41 invested in workforce safety, diversity and training.",
      "source_sentence": "In FY2023, Default ASEAN 41 invested in workforce safety, diversity and training.",
      "source_page": 1
    },
    {
      "text": "In FY2023, Default ASEAN 41 improved energy, water and waste circularity.",
      "source_sentence": "In FY2023, Default ASEAN 41 improved energy, water and waste circularity.",
      "source_page": 1
    },
    {
      "text": "In FY2023, Default ASEAN 41 strengthened data governance, cyber and privacy risk management.",
      "source_sentence": "In FY2023, Default ASEAN 41 strengthened data governance, cyber and privacy risk management.",
      "source_page": 1
    }
  ]
}